{"file":"cardsplit.png","frames":{
"plist_puke_value_0_2":{"x":31,"y":182,"w":28,"h":43,"offX":0,"offY":0,"sourceW":28,"sourceH":43},
"plist_puke_value_0_3":{"x":140,"y":92,"w":29,"h":44,"offX":0,"offY":0,"sourceW":29,"sourceH":44},
"plist_puke_value_0_4":{"x":70,"y":97,"w":29,"h":42,"offX":0,"offY":0,"sourceW":29,"sourceH":42},
"plist_puke_value_0_5":{"x":1,"y":143,"w":28,"h":43,"offX":0,"offY":0,"sourceW":28,"sourceH":43},
"plist_puke_value_0_6":{"x":205,"y":46,"w":29,"h":44,"offX":0,"offY":0,"sourceW":29,"sourceH":44},
"plist_puke_value_0_7":{"x":1,"y":188,"w":28,"h":42,"offX":0,"offY":0,"sourceW":28,"sourceH":42},
"plist_puke_value_0_8":{"x":174,"y":46,"w":29,"h":44,"offX":0,"offY":0,"sourceW":29,"sourceH":44},
"plist_puke_value_0_9":{"x":109,"y":51,"w":29,"h":44,"offX":0,"offY":0,"sourceW":29,"sourceH":44},
"plist_puke_value_0_10":{"x":53,"y":1,"w":50,"h":44,"offX":0,"offY":0,"sourceW":50,"sourceH":44},
"plist_puke_value_0_11":{"x":131,"y":138,"w":25,"h":44,"offX":0,"offY":0,"sourceW":25,"sourceH":44},
"plist_puke_value_0_12":{"x":105,"y":1,"w":36,"h":48,"offX":0,"offY":0,"sourceW":36,"sourceH":48},
"plist_puke_value_0_13":{"x":217,"y":1,"w":33,"h":43,"offX":0,"offY":0,"sourceW":33,"sourceH":43},
"plist_puke_value_1_1":{"x":143,"y":1,"w":37,"h":43,"offX":0,"offY":0,"sourceW":37,"sourceH":43},
"plist_puke_value_1_2":{"x":101,"y":97,"w":28,"h":43,"offX":0,"offY":0,"sourceW":28,"sourceH":43},
"plist_puke_value_1_3":{"x":1,"y":97,"w":29,"h":44,"offX":0,"offY":0,"sourceW":29,"sourceH":44},
"plist_puke_value_1_4":{"x":32,"y":138,"w":29,"h":42,"offX":0,"offY":0,"sourceW":29,"sourceH":42},
"plist_puke_value_1_5":{"x":63,"y":141,"w":28,"h":43,"offX":0,"offY":0,"sourceW":28,"sourceH":43},
"plist_puke_value_1_6":{"x":39,"y":92,"w":29,"h":44,"offX":0,"offY":0,"sourceW":29,"sourceH":44},
"plist_puke_value_1_7":{"x":61,"y":186,"w":28,"h":42,"offX":0,"offY":0,"sourceW":28,"sourceH":42},
"plist_puke_value_1_8":{"x":78,"y":51,"w":29,"h":44,"offX":0,"offY":0,"sourceW":29,"sourceH":44},
"plist_puke_value_1_9":{"x":143,"y":46,"w":29,"h":44,"offX":0,"offY":0,"sourceW":29,"sourceH":44},
"plist_puke_value_1_10":{"x":1,"y":1,"w":50,"h":44,"offX":0,"offY":0,"sourceW":50,"sourceH":44},
"plist_puke_value_1_11":{"x":131,"y":184,"w":25,"h":44,"offX":0,"offY":0,"sourceW":25,"sourceH":44},
"plist_puke_value_1_12":{"x":1,"y":47,"w":36,"h":48,"offX":0,"offY":0,"sourceW":36,"sourceH":48},
"plist_puke_value_1_13":{"x":182,"y":1,"w":33,"h":43,"offX":0,"offY":0,"sourceW":33,"sourceH":43},
"csp_caohua":{"x":91,"y":186,"w":33,"h":32,"offX":0,"offY":0,"sourceW":33,"sourceH":32},
"csp_dawang":{"x":236,"y":46,"w":18,"h":62,"offX":0,"offY":0,"sourceW":18,"sourceH":62},
"csp_fangkuai":{"x":91,"y":220,"w":32,"h":32,"offX":0,"offY":0,"sourceW":32,"sourceH":32},
"csp_heitao":{"x":93,"y":142,"w":32,"h":32,"offX":0,"offY":0,"sourceW":32,"sourceH":32},
"csp_hongtao":{"x":191,"y":92,"w":33,"h":30,"offX":0,"offY":0,"sourceW":33,"sourceH":30},
"csp_xiaowang":{"x":171,"y":92,"w":18,"h":62,"offX":0,"offY":0,"sourceW":18,"sourceH":62},
"plist_puke_value_0_1":{"x":39,"y":47,"w":37,"h":43,"offX":0,"offY":0,"sourceW":37,"sourceH":43}}}