{"width":1024,"imagePath":"lhdz_vs_tex.png","SubTexture":[{"width":46,"y":1,"height":46,"name":"hhdz_vshei","x":928},{"width":59,"y":947,"height":59,"name":"hhdz_gd","x":616},{"width":613,"y":544,"height":182,"name":"lhd_vslongdb","x":1},{"frameWidth":413,"y":1,"frameHeight":366,"width":407,"frameX":-2,"height":357,"name":"lhd_vslong","frameY":-6,"x":1},{"frameWidth":210,"y":299,"frameHeight":43,"width":205,"frameX":0,"height":43,"name":"lhd_vslongwatertw","frameY":0,"x":410},{"frameWidth":395,"y":728,"frameHeight":174,"width":394,"frameX":0,"height":173,"name":"lhd_vslongwater","frameY":-1,"x":435},{"width":619,"y":360,"height":182,"name":"lhd_vshudb","x":1},{"frameWidth":390,"y":1,"frameHeight":313,"width":388,"frameX":-1,"height":296,"name":"lhd_vshu","frameY":-16,"x":410},{"width":220,"y":181,"height":55,"name":"lhd_vshufiretw","x":800},{"frameWidth":434,"y":728,"frameHeight":223,"width":432,"frameX":-1,"height":223,"name":"lhd_vshufire","frameY":0,"x":1},{"frameWidth":184,"y":947,"frameHeight":46,"width":179,"frameX":-3,"height":33,"name":"hhdz_pz2","frameY":-7,"x":435},{"frameWidth":184,"y":708,"frameHeight":46,"width":179,"frameX":-3,"height":12,"name":"hhdz_pz4","frameY":-17,"x":616},{"frameWidth":184,"y":903,"frameHeight":46,"width":170,"frameX":-7,"height":42,"name":"hhdz_pz1","frameY":-2,"x":435},{"frameWidth":184,"y":344,"frameHeight":46,"width":182,"frameX":0,"height":14,"name":"hhdz_pz3","frameY":-16,"x":410},{"frameWidth":166,"y":708,"frameHeight":165,"width":166,"frameX":0,"height":164,"name":"lhd_vstexts","frameY":0,"x":831},{"frameWidth":127,"y":1,"frameHeight":179,"width":126,"frameX":-1,"height":178,"name":"lhd_vstextv","frameY":0,"x":800},{"width":170,"y":903,"height":42,"name":"hhdz_gt","x":607},{"width":53,"y":947,"height":42,"name":"hhdz_xg4","x":736},{"width":97,"y":238,"height":43,"name":"hhdz_xg5","x":800},{"width":300,"y":544,"height":162,"name":"lhd_tigger","x":616},{"frameWidth":281,"y":299,"frameHeight":216,"width":281,"frameX":0,"height":214,"name":"lhd_loong","frameY":0,"x":622},{"frameWidth":186,"y":874,"frameHeight":122,"width":171,"frameX":-11,"height":120,"name":"lhd_vslizi","frameY":-2,"x":831},{"frameWidth":59,"y":947,"frameHeight":50,"width":57,"frameX":-1,"height":48,"name":"lhd_vslongld1","frameY":-1,"x":677},{"frameWidth":102,"y":238,"frameHeight":122,"width":100,"frameX":-1,"height":120,"name":"lhd_vslongld2","frameY":-1,"x":905}],"height":1024,"name":"lhdz_vs"}