{"file":"brnn_zjcx.png","frames":{
"qznnresult_card_spade6":{"x":1271,"y":423,"w":58,"h":80,"offX":0,"offY":0,"sourceW":58,"sourceH":80},
"qznnresult_card_spade5":{"x":1931,"y":421,"w":58,"h":80,"offX":0,"offY":0,"sourceW":58,"sourceH":80},
"qznnresult_card_spade4":{"x":1871,"y":421,"w":58,"h":80,"offX":0,"offY":0,"sourceW":58,"sourceH":80},
"qznnresult_card_spade3":{"x":1811,"y":421,"w":58,"h":80,"offX":0,"offY":0,"sourceW":58,"sourceH":80},
"qznnresult_card_spade2":{"x":1631,"y":409,"w":58,"h":80,"offX":0,"offY":0,"sourceW":58,"sourceH":80},
"qznnresult_card_spade1":{"x":1211,"y":377,"w":58,"h":80,"offX":0,"offY":0,"sourceW":58,"sourceH":80},
"qznnresult_card_heart13":{"x":1151,"y":377,"w":58,"h":80,"offX":0,"offY":0,"sourceW":58,"sourceH":80},
"qznnresult_card_heart12":{"x":1751,"y":363,"w":58,"h":80,"offX":0,"offY":0,"sourceW":58,"sourceH":80},
"qznnresult_card_heart11":{"x":1091,"y":356,"w":58,"h":80,"offX":0,"offY":0,"sourceW":58,"sourceH":80},
"qznnresult_card_heart10":{"x":1571,"y":350,"w":58,"h":80,"offX":0,"offY":0,"sourceW":58,"sourceH":80},
"qznnresult_card_heart9":{"x":1511,"y":350,"w":58,"h":80,"offX":0,"offY":0,"sourceW":58,"sourceH":80},
"qznnresult_card_heart8":{"x":1451,"y":350,"w":58,"h":80,"offX":0,"offY":0,"sourceW":58,"sourceH":80},
"qznnresult_card_heart7":{"x":1691,"y":342,"w":58,"h":80,"offX":0,"offY":0,"sourceW":58,"sourceH":80},
"qznnresult_card_heart6":{"x":1391,"y":341,"w":58,"h":80,"offX":0,"offY":0,"sourceW":58,"sourceH":80},
"qznnresult_card_heart5":{"x":1331,"y":341,"w":58,"h":80,"offX":0,"offY":0,"sourceW":58,"sourceH":80},
"qznnresult_card_heart4":{"x":1271,"y":341,"w":58,"h":80,"offX":0,"offY":0,"sourceW":58,"sourceH":80},
"qznnresult_card_heart3":{"x":1953,"y":339,"w":58,"h":80,"offX":0,"offY":0,"sourceW":58,"sourceH":80},
"qznnresult_card_heart2":{"x":1893,"y":339,"w":58,"h":80,"offX":0,"offY":0,"sourceW":58,"sourceH":80},
"qznnresult_card_heart1":{"x":1833,"y":339,"w":58,"h":80,"offX":0,"offY":0,"sourceW":58,"sourceH":80},
"qznnresult_card_diamond13":{"x":1631,"y":327,"w":58,"h":80,"offX":0,"offY":0,"sourceW":58,"sourceH":80},
"qznnresult_card_diamond12":{"x":1211,"y":295,"w":58,"h":80,"offX":0,"offY":0,"sourceW":58,"sourceH":80},
"qznnresult_card_diamond11":{"x":1151,"y":295,"w":58,"h":80,"offX":0,"offY":0,"sourceW":58,"sourceH":80},
"qznnresult_card_diamond10":{"x":1773,"y":281,"w":58,"h":80,"offX":0,"offY":0,"sourceW":58,"sourceH":80},
"qznnresult_card_diamond9":{"x":1091,"y":274,"w":58,"h":80,"offX":0,"offY":0,"sourceW":58,"sourceH":80},
"qznnresult_card_diamond8":{"x":1571,"y":268,"w":58,"h":80,"offX":0,"offY":0,"sourceW":58,"sourceH":80},
"qznnresult_card_diamond7":{"x":1511,"y":268,"w":58,"h":80,"offX":0,"offY":0,"sourceW":58,"sourceH":80},
"qznnresult_card_diamond6":{"x":1451,"y":268,"w":58,"h":80,"offX":0,"offY":0,"sourceW":58,"sourceH":80},
"qznnresult_card_diamond5":{"x":1713,"y":260,"w":58,"h":80,"offX":0,"offY":0,"sourceW":58,"sourceH":80},
"qznnresult_card_diamond4":{"x":1391,"y":259,"w":58,"h":80,"offX":0,"offY":0,"sourceW":58,"sourceH":80},
"qznnresult_card_diamond3":{"x":1331,"y":259,"w":58,"h":80,"offX":0,"offY":0,"sourceW":58,"sourceH":80},
"qznnresult_card_diamond2":{"x":1271,"y":259,"w":58,"h":80,"offX":0,"offY":0,"sourceW":58,"sourceH":80},
"qznnresult_card_diamond1":{"x":1965,"y":257,"w":58,"h":80,"offX":0,"offY":0,"sourceW":58,"sourceH":80},
"qznnresult_card_club13":{"x":1905,"y":257,"w":58,"h":80,"offX":0,"offY":0,"sourceW":58,"sourceH":80},
"qznnresult_card_club12":{"x":1845,"y":257,"w":58,"h":80,"offX":0,"offY":0,"sourceW":58,"sourceH":80},
"qznnresult_card_club11":{"x":1653,"y":245,"w":58,"h":80,"offX":0,"offY":0,"sourceW":58,"sourceH":80},
"qznnresult_card_club10":{"x":1211,"y":213,"w":58,"h":80,"offX":0,"offY":0,"sourceW":58,"sourceH":80},
"qznnresult_card_club9":{"x":1151,"y":213,"w":58,"h":80,"offX":0,"offY":0,"sourceW":58,"sourceH":80},
"qznnresult_card_club8":{"x":1785,"y":199,"w":58,"h":80,"offX":0,"offY":0,"sourceW":58,"sourceH":80},
"qznnresult_card_club7":{"x":1091,"y":192,"w":58,"h":80,"offX":0,"offY":0,"sourceW":58,"sourceH":80},
"qznnresult_card_club6":{"x":1593,"y":186,"w":58,"h":80,"offX":0,"offY":0,"sourceW":58,"sourceH":80},
"qznnresult_card_club5":{"x":1533,"y":186,"w":58,"h":80,"offX":0,"offY":0,"sourceW":58,"sourceH":80},
"qznnresult_card_club4":{"x":1473,"y":186,"w":58,"h":80,"offX":0,"offY":0,"sourceW":58,"sourceH":80},
"qznnresult_card_club3":{"x":1725,"y":178,"w":58,"h":80,"offX":0,"offY":0,"sourceW":58,"sourceH":80},
"qznnresult_card_club2":{"x":1413,"y":177,"w":58,"h":80,"offX":0,"offY":0,"sourceW":58,"sourceH":80},
"qznnresult_card_club1":{"x":1353,"y":177,"w":58,"h":80,"offX":0,"offY":0,"sourceW":58,"sourceH":80},
"qznn_niu12":{"x":1813,"y":53,"w":100,"h":62,"offX":0,"offY":1,"sourceW":100,"sourceH":63},
"qznn_niu11":{"x":1583,"y":125,"w":80,"h":59,"offX":0,"offY":0,"sourceW":80,"sourceH":59},
"qznn_niu10":{"x":1501,"y":125,"w":80,"h":59,"offX":3,"offY":1,"sourceW":86,"sourceH":61},
"qznn_niu9":{"x":1755,"y":117,"w":80,"h":59,"offX":3,"offY":1,"sourceW":86,"sourceH":61},
"qznn_niu8":{"x":1419,"y":116,"w":80,"h":59,"offX":3,"offY":1,"sourceW":86,"sourceH":61},
"qznn_niu7":{"x":1337,"y":116,"w":80,"h":59,"offX":3,"offY":1,"sourceW":86,"sourceH":61},
"qznn_niu6":{"x":1915,"y":114,"w":80,"h":59,"offX":3,"offY":1,"sourceW":86,"sourceH":61},
"qznn_niu5":{"x":1673,"y":102,"w":80,"h":59,"offX":3,"offY":1,"sourceW":86,"sourceH":61},
"qznn_niu4":{"x":1255,"y":70,"w":80,"h":59,"offX":3,"offY":1,"sourceW":86,"sourceH":61},
"qznn_niu3":{"x":1173,"y":70,"w":80,"h":59,"offX":3,"offY":1,"sourceW":86,"sourceH":61},
"qznn_niu2":{"x":1091,"y":70,"w":80,"h":59,"offX":3,"offY":1,"sourceW":86,"sourceH":61},
"qznn_niu1":{"x":1915,"y":53,"w":80,"h":59,"offX":3,"offY":1,"sourceW":86,"sourceH":61},
"qznn_niu0":{"x":1091,"y":131,"w":80,"h":59,"offX":3,"offY":1,"sourceW":86,"sourceH":61},
"brnn_zjcx_title":{"x":1765,"y":0,"w":241,"h":51,"offX":0,"offY":0,"sourceW":241,"sourceH":51},
"brnn_zjcx_line":{"x":1042,"y":726,"w":965,"h":5,"offX":0,"offY":0,"sourceW":965,"sourceH":5},
"brnn_zjcx_level3":{"x":1091,"y":459,"w":107,"h":38,"offX":0,"offY":0,"sourceW":107,"sourceH":38},
"brnn_zjcx_level2":{"x":1691,"y":445,"w":107,"h":38,"offX":0,"offY":0,"sourceW":107,"sourceH":38},
"brnn_zjcx_level1":{"x":1464,"y":432,"w":107,"h":38,"offX":0,"offY":0,"sourceW":107,"sourceH":38},
"brnn_zjcx_imgnobet":{"x":1673,"y":53,"w":138,"h":47,"offX":0,"offY":0,"sourceW":138,"sourceH":47},
"brnn_zjcx_iconwin":{"x":1331,"y":423,"w":65,"h":66,"offX":0,"offY":0,"sourceW":65,"sourceH":66},
"brnn_zjcx_iconlose":{"x":1398,"y":432,"w":64,"h":66,"offX":0,"offY":0,"sourceW":64,"sourceH":66},
"brnn_zjcx_iconbanker":{"x":1997,"y":53,"w":47,"h":50,"offX":0,"offY":0,"sourceW":47,"sourceH":50},
"brnn_zjcx_icon4":{"x":1997,"y":105,"w":46,"h":46,"offX":3,"offY":4,"sourceW":51,"sourceH":52},
"brnn_zjcx_icon3":{"x":1991,"y":421,"w":45,"h":45,"offX":4,"offY":3,"sourceW":52,"sourceH":50},
"brnn_zjcx_icon2":{"x":1845,"y":199,"w":45,"h":45,"offX":3,"offY":0,"sourceW":50,"sourceH":45},
"brnn_zjcx_icon1":{"x":1337,"y":70,"w":46,"h":43,"offX":3,"offY":5,"sourceW":51,"sourceH":51},
"brnn_zjcx_btndetail":{"x":1519,"y":53,"w":152,"h":70,"offX":0,"offY":0,"sourceW":152,"sourceH":70},
"brnn_zjcx_bglabel":{"x":1519,"y":0,"w":244,"h":51,"offX":0,"offY":0,"sourceW":244,"sourceH":51},
"brnn_zjcx_bg":{"x":0,"y":0,"w":1089,"h":724,"offX":0,"offY":0,"sourceW":1089,"sourceH":724},
"brnn_room_zjcxbtn":{"x":1403,"y":0,"w":114,"h":114,"offX":0,"offY":0,"sourceW":114,"sourceH":114},
"qznnresult_card_spade13":{"x":1837,"y":117,"w":58,"h":80,"offX":0,"offY":0,"sourceW":58,"sourceH":80},
"qznnresult_card_spade12":{"x":1293,"y":177,"w":58,"h":80,"offX":0,"offY":0,"sourceW":58,"sourceH":80},
"qznnresult_card_spade11":{"x":1957,"y":175,"w":58,"h":80,"offX":0,"offY":0,"sourceW":58,"sourceH":80},
"qznnresult_card_spade10":{"x":1897,"y":175,"w":58,"h":80,"offX":0,"offY":0,"sourceW":58,"sourceH":80},
"qznnresult_card_spade9":{"x":1665,"y":163,"w":58,"h":80,"offX":0,"offY":0,"sourceW":58,"sourceH":80},
"qznnresult_card_spade8":{"x":1233,"y":131,"w":58,"h":80,"offX":0,"offY":0,"sourceW":58,"sourceH":80},
"qznnresult_card_spade7":{"x":1173,"y":131,"w":58,"h":80,"offX":0,"offY":0,"sourceW":58,"sourceH":80},
"brnn_zjcx_bgpanel":{"x":0,"y":726,"w":1040,"h":567,"offX":0,"offY":0,"sourceW":1040,"sourceH":567},
"brnn_zjcx_bgpanellabel":{"x":1091,"y":0,"w":310,"h":68,"offX":0,"offY":0,"sourceW":310,"sourceH":68}}}